cherab_lhd.dylibs/libomp.dylib
cherab_lhd-0.2.0.dist-info/LICENSE.md
cherab_lhd-0.2.0.dist-info/RECORD
cherab_lhd-0.2.0.dist-info/WHEEL
cherab_lhd-0.2.0.dist-info/METADATA
cherab/lhd/version.py
cherab/lhd/__init__.py
cherab/lhd/tools/fetch.py
cherab/lhd/tools/utility.py
cherab/lhd/tools/samplers.cpython-311-darwin.so
cherab/lhd/tools/__init__.py
cherab/lhd/tools/visualization.py
cherab/lhd/tools/urls.json
cherab/lhd/tools/spinner.py
cherab/lhd/tools/registries.json
cherab/lhd/emc3/grid.py
cherab/lhd/emc3/barycenters.py
cherab/lhd/emc3/__init__.py
cherab/lhd/emc3/plasma.py
cherab/lhd/emc3/indices.py
cherab/lhd/emc3/curvilinear.py
cherab/lhd/emc3/raytransfer/emitters.cpython-311-darwin.so
cherab/lhd/emc3/raytransfer/__init__.py
cherab/lhd/emc3/raytransfer/raytransfer.py
cherab/lhd/emc3/repository/utility.py
cherab/lhd/emc3/repository/__init__.py
cherab/lhd/emc3/repository/install.py
cherab/lhd/emc3/repository/parse.py
cherab/lhd/emc3/inversion/polygon.cpython-311-darwin.so
cherab/lhd/emc3/inversion/__init__.py
cherab/lhd/emc3/inversion/derivative.py
cherab/lhd/emc3/cython/mapper.pxd
cherab/lhd/emc3/cython/intfunction.pxd
cherab/lhd/emc3/cython/utility.cpython-311-darwin.so
cherab/lhd/emc3/cython/__init__.pxd
cherab/lhd/emc3/cython/__init__.py
cherab/lhd/emc3/cython/intfunction.cpython-311-darwin.so
cherab/lhd/emc3/cython/discrete3dmesh.pxd
cherab/lhd/emc3/cython/masking.pxd
cherab/lhd/emc3/cython/tetrahedralization.pxd
cherab/lhd/emc3/cython/tetrahedralization.cpython-311-darwin.so
cherab/lhd/emc3/cython/mapper.cpython-311-darwin.so
cherab/lhd/emc3/cython/discrete3dmesh.cpython-311-darwin.so
cherab/lhd/emc3/cython/tetra_mesh.cpython-311-darwin.so
cherab/lhd/emc3/cython/masking.cpython-311-darwin.so
cherab/lhd/observer/__init__.py
cherab/lhd/observer/imaging/__init__.py
cherab/lhd/observer/imaging/pinhole.cpython-311-darwin.so
cherab/lhd/observer/bolometer/__init__.py
cherab/lhd/observer/bolometer/load_irvb.py
cherab/lhd/observer/bolometer/load_resistive.py
cherab/lhd/observer/bolometer/irvb.py
cherab/lhd/machine/wall.py
cherab/lhd/machine/__init__.py
