Metadata-Version: 2.1
Name: cherab-lhd
Version: 0.2.0
Summary: Cherab spectroscopy framework: LHD machine configuration
Author-Email: Koyo Munechika <munechika.koyo@torus.nr.titech.ac.jp>
Maintainer-Email: Koyo Munechika <munechika.koyo@torus.nr.titech.ac.jp>
License: BSD 3-Clause License
Classifier: Development Status :: 4 - Beta
Classifier: Intended Audience :: Science/Research
Classifier: Intended Audience :: Education
Classifier: Intended Audience :: Developers
Classifier: License :: OSI Approved :: BSD License
Classifier: Natural Language :: English
Classifier: Operating System :: POSIX :: Linux
Classifier: Operating System :: MacOS
Classifier: Programming Language :: Cython
Classifier: Programming Language :: Python :: 3.10
Classifier: Programming Language :: Python :: 3.11
Classifier: Programming Language :: Python :: 3.12
Classifier: Topic :: Scientific/Engineering :: Physics
Project-URL: Homepage, https://cherab-lhd.readthedocs.io
Project-URL: documentation, https://cherab-lhd.readthedocs.io
Project-URL: repository, https://github.com/munechika-koyo/cherab_lhd
Requires-Python: >=3.10
Requires-Dist: numpy<2.0,>=1.14
Requires-Dist: scipy
Requires-Dist: matplotlib
Requires-Dist: plotly
Requires-Dist: h5py
Requires-Dist: xarray
Requires-Dist: netcdf4
Requires-Dist: cherab<2.0,>=1.5
Requires-Dist: rich
Requires-Dist: pooch
Requires-Dist: paramiko
Requires-Dist: tqdm
